{
  "title": "Build a Datadog Integrations - Advanced Workshop Dash 2019",
  "description": "Build a Datadog Integrations from scratch",
  "details": {
    "steps": [
      {
        "title": "Step 1",
        "text": "step1.md"
      },
      {
        "title": "Step 2",
        "text": "step2.md"
      },
      {
        "title": "Step 3",
        "text": "step3.md"
      }
    ],
    "intro": {
      "text": "intro.md"
    },
    "finish": {
      "text": "finish.md"
    }
  },
  "environment": {
    "uilayout": "editor-terminal"
  },
  "backend": {
    "imageid": "ubuntu"
  }
}
